Workbook

Sheet Read Me
A1: Volt Library Catalogue
A2: Master data for the Volt Library directory app. Researched and checked as of October 29, 2026.
A4: At a glance
A5: Resources | B5: =COUNTA(Resources!A:A)-1 -> 353
A6: Sections | B6: =COUNTA(Sections!A:A)-1 -> 13
A7: Links verified | B7: =COUNTIF(Resources!S:S,"Verified")+COUNTIF(Resources!S:S,"Found in search") -> 351
A8: Links that need a check | B8: =COUNTIF(Resources!S:S,"Needs check") -> 2
A9: Kept from the Notion library | B9: =COUNTIF(Resources!R:R,"Notion import") -> 42
A10: Removed entries (see Removed tab) | B10: =COUNTA(Removed!A:A)-1 -> 51
A12: How to use it
A13: Resources tab | B13: One row per resource. This is the tab the app reads. Filter by Section, Topics, Status or Link Check.
A14: Adding a resource | B14: Add a row at the bottom. Use the next ID for its section (e.g. LAW-036), pick Section from the dropdown, and fill at least Name, Topics, Description and URL.
A15: Editing | B15: Edit any cell directly. When you re-check a link or a date, set Link Check and update Last Checked.
A16: Grey rows | B16: An event whose End Date has passed turns grey automatically. Remove it or replace it with the next edition.
A17: Amber cells | B17: Link Check = Needs check. The URL is the official address as far as known but was not opened during research. Check these before launch.
A18: Sections tab | B18: The app's section list: key, code, display name and description, with live counts.
A19: Coverage tab | B19: Counts by section and topic, to spot gaps (for example, few AI entries in a section).
A20: Removed tab | B20: Entries dropped from the library, and why.
A22: Columns
A23: ID | B23: Section code + number. Stable; never reuse an ID.
A24: Name | B24: Display name in the app.
A25: Section / Section Key | B25: Display name and the key the app uses (laws, regulators, frameworks, certifications, learning, events, research, news, podcasts, books, tools, communities, jobs).
A26: Type | B26: What kind of resource it is (Law, Framework, Certification, Podcast, Job board...). Shown as the small label under the name.
A27: Topics | B27: Semicolon-separated, from: Cybersecurity; Privacy; AI; Tech Law; General.
A28: Description | B28: One plain sentence, 160 characters or fewer.
A29: URL | B29: Official page. No affiliate links.
A30: Publisher | B30: Issuing body, organizer, host or author's publisher.
A31: Jurisdiction | B31: Where it applies or is based: Global, EU, UK, US, US-CA, Nigeria, etc.
A32: Level | B32: Beginner, Intermediate, Advanced or All (learning, certifications, books, events).
A33: Cost | B33: Free, Freemium, Paid, or a price note. Prices are as of the Last Checked date.
A34: Format | B34: Online, In person, Hybrid, Audio, Print/ebook, Exam, Download, Software.
... A41: Curator Notes | B41: Key dates, versions, fees, prerequisites and what to watch. Not shown in the app.
A43: Updating the app
A44: Data | B44: Each Resources row becomes one entry in the app's DATA list: Name, Section Key, Type, Topics (as codes c, p, a, l, g), URL, and for events {when, end, loc, cost} from Start/End Date, Location and Cost.
A45: Sections | B45: The app currently has 7 sections; this catalogue has 13. Replace the app's CATS list with the Sections tab (key, code, name, description).
A46: New topic | B46: Tech Law (code l) is new. Add it to the app's TOPICS list and give it a colour.
A47: Descriptions | B47: The app does not show descriptions yet. Add one line under each name using the Description column.

Sheet Resources
A1: ID | B1: Name | C1: Section | D1: Section Key | E1: Type | F1: Topics | G1: Description | H1: URL | I1: Publisher | J1: Jurisdiction | K1: Level | L1: Cost | M1: Format | N1: Start Date | O1: End Date | P1: Location | Q1: Status | R1: Origin | S1: Link Check | T1: Last Checked | U1: Curator Notes
A2: LAW-001 | B2: General Data Protection Regulation (Regulation (EU) 2016/679) | C2: Laws & Regulations | D2: laws | E2: Regulation | F2: Privacy | G2: EU regulation setting rules for processing personal data, data subject rights, controller and processor duties, transfers and fines. | H2: https://eur-lex.europa.eu/eli/reg/2016/679/oj/eng | I2: European Parliament and Council of the EU | J2: EU | L2: Free | M2: Online | N2: 43245 | Q2: In force | R2: New | S2: Verified | T2: 46324 | U2: Applies since May 25, 2018. Digital Omnibus proposal (COM(2025) 837) would amend GDPR and move cookie rules into it; no Council mandate or trilogue as of mid-Oct 2026. Watch for end-2026 deal push.
A3: LAW-002 | B3: EU Artificial Intelligence Act (Regulation (EU) 2024/1689) | C3: Laws & Regulations | D3: laws | E3: Regulation | F3: AI | G3: Risk-based EU rules for AI systems and general-purpose AI models: prohibited practices, high-risk requirements, transparency and governance. | H3: https://eur-lex.europa.eu/eli/reg/2024/1689/oj/eng | I3: European Parliament and Council of the EU | J3: EU | L3: Free | M3: Online | Q3: Partly in force | R3: New | S3: Verified | T3: 46324 | U3: In force Aug 1, 2024. Bans and AI literacy Feb 2, 2025; GPAI Aug 2, 2025; Art. 50 transparency Aug 2, 2026. AI Omnibus Reg. (EU) 2026/1744 (in force Jul 27, 2026) moved Annex III high-risk to Dec 2, 2027 and Annex I to Aug 2, 2028.
A4: LAW-003 | B4: NIS2 Directive (Directive (EU) 2022/2555) | C4: Laws & Regulations | D4: laws | E4: Directive | F4: Cybersecurity | G4: EU directive requiring essential and important entities in critical sectors to manage cybersecurity risk and report significant incidents. | H4: https://eur-lex.europa.eu/eli/dir/2022/2555/oj/eng | I4: European Parliament and Council of the EU | J4: EU | L4: Free | M4: Online | N4: 45583 | Q4: In force | R4: New | S4: Verified | T4: 46324 | U4: Transposition deadline Oct 17, 2024; national measures apply from Oct 18, 2024. Obligations arise through national laws, so check each Member State's transposition. 24-hour early warning and 72-hour incident notification.
A5: LAW-004 | B5: Digital Operational Resilience Act (DORA) (Regulation (EU) 2022/2554) | C5: Laws & Regulations | D5: laws | E5: Regulation | F5: Cybersecurity | G5: EU regulation on ICT risk management, incident reporting, resilience testing and third-party ICT risk for financial entities. | H5: https://eur-lex.europa.eu/eli/reg/2022/2554/oj/eng | I5: European Parliament and Council of the EU | J5: EU | L5: Free | M5: Online | N5: 45674 | Q5: In force | R5: New | S5: Verified | T5: 46324 | U5: Applies from Jan 17, 2025, with supporting RTS/ITS technical standards. Includes an oversight framework for critical ICT third-party service providers run by the European Supervisory Authorities.
A6: LAW-005 | B6: Cyber Resilience Act (Regulation (EU) 2024/2847) | C6: Laws & Regulations | D6: laws | E6: Regulation | F6: Cybersecurity | G6: EU regulation setting cybersecurity requirements for hardware and software products with digital elements across their lifecycle. | H6: https://eur-lex.europa.eu/eli/reg/2024/2847/oj/eng | I6: European Parliament and Council of the EU | J6: EU | L6: Free | M6: Online | Q6: Partly in force | R6: New | S6: Verified | T6: 46324 | U6: In force Dec 10, 2024. Manufacturer reporting of actively exploited vulnerabilities and severe incidents applies from Sep 11, 2026 (to CSIRTs and ENISA). Most obligations apply from Dec 11, 2027.
A7: LAW-006 | B7: EU Data Act (Regulation (EU) 2023/2854) | C7: Laws & Regulations | D7: laws | E7: Regulation | F7: Tech Law; Privacy | G7: EU regulation on access to and use of data from connected products and related services, B2B data sharing terms and cloud switching. | H7: https://eur-lex.europa.eu/eli/reg/2023/2854/oj/eng | I7: European Parliament and Council of the EU | J7: EU | L7: Free | M7: Online | N7: 45912 | Q7: In force | R7: New | S7: Verified | T7: 46324 | U7: Applies from Sep 12, 2025. Access-by-design duties for products placed on market after Sep 12, 2026. Unfair-terms rules reach older contracts from Sep 12, 2027. Digital Omnibus proposes amendments (pending).
A8: LAW-007 | B8: ePrivacy Directive (Directive 2002/58/EC) | C8: Laws & Regulations | D8: laws | E8: Directive | F8: Privacy | G8: EU directive on privacy in electronic communications, covering confidentiality, cookies and similar tracking, traffic data and direct marketing. | H8: https://eur-lex.europa.eu/eli/dir/2002/58/oj/eng | I8: European Parliament and Council of the EU | J8: EU | L8: Free | M8: Online | Q8: In force | R8: New | S8: Verified | T8: 46324 | U8: Amended 2009 (cookie consent). Applied through national laws. The proposed ePrivacy Regulation was withdrawn in 2025; the pending Digital Omnibus would move cookie/terminal-device rules into the GDPR.
A9: LAW-008 | B9: UK GDPR and Data Protection Act 2018 | C9: Laws & Regulations | D9: laws | E9: Law | F9: Privacy | G9: UK framework for personal data processing: the Act supplements the retained UK GDPR and covers law enforcement and intelligence processing. | H9: https://www.legislation.gov.uk/ukpga/2018/12/contents | I9: UK Parliament | J9: UK | L9: Free | M9: Online | N9: 43245 | Q9: In force | R9: New | S9: Verified | T9: 46324 | U9: UK GDPR is the retained version of EU GDPR. Both were substantially amended by the Data (Use and Access) Act 2025, with main changes in force from Feb 5, 2026.
A10: LAW-009 | B10: Data (Use and Access) Act 2025 | C10: Laws & Regulations | D10: laws | E10: Law | F10: Privacy; Tech Law | G10: UK Act amending UK GDPR, DPA 2018 and PECR, creating smart data and digital verification regimes, and restructuring the ICO. | H10: https://www.legislation.gov.uk/ukpga/2025/18/contents | I10: UK Parliament | J10: UK | L10: Free | M10: Online | Q10: Partly in force | R10: New | S10: Verified | T10: 46324 | U10: Royal Assent Jun 19, 2025. Main data protection changes in force Feb 5, 2026 (Commencement No. 6). Complaints-handling duty from Jun 19, 2026. ICO became the Information Commission on Sep 30, 2026. Some provisions still commencing.
A11: LAW-010 | B11: HIPAA Privacy, Security and Breach Notification Rules (45 CFR Parts 160 and 164) | C11: Laws & Regulations | D11: laws | E11: Regulation | F11: Privacy; Cybersecurity | G11: US federal rules governing use, disclosure and security of protected health information by covered entities and business associates. | H11: https://www.ecfr.gov/current/title-45/subtitle-A/subchapter-C/part-164 | I11: U.S. Department of Health and Human Services | J11: US | L11: Free | M11: Online | Q11: In force | R11: New | S11: Verified | T11: 46324 | U11: Enforced by HHS OCR. Proposed Security Rule overhaul (NPRM Jan 2025: MFA, encryption, asset inventory) has not been finalized; HHS has signalled final action in 2027.
A12: LAW-011 | B12: GLBA Safeguards Rule (16 CFR Part 314) | C12: Laws & Regulations | D12: laws | E12: Regulation | F12: Cybersecurity; Privacy | G12: FTC rule under the Gramm-Leach-Bliley Act requiring non-bank financial institutions to run an information security program. | H12: https://www.ecfr.gov/current/title-16/chapter-I/subchapter-C/part-314 | I12: Federal Trade Commission | J12: US | L12: Free | M12: Online | Q12: In force | R12: New | S12: Verified | T12: 46324 | U12: Amended 2021 (specific program elements, compliance from Jun 9, 2023). Breach notice to FTC for events affecting 500+ consumers effective May 13, 2024 (16 CFR 314.4(j)).
A13: LAW-012 | B13: Children's Online Privacy Protection Rule (COPPA Rule) (16 CFR Part 312) | C13: Laws & Regulations | D13: laws | E13: Regulation | F13: Privacy | G13: FTC rule requiring verifiable parental consent and data limits for online services directed to, or knowingly collecting data from, children under 13. | H13: https://www.ecfr.gov/current/title-16/chapter-I/subchapter-C/part-312 | I13: Federal Trade Commission | J13: US | L13: Free | M13: Online | Q13: In force | R13: New | S13: Verified | T13: 46324 | U13: Amended rule published Apr 22, 2025 (90 FR 16977), effective Jun 23, 2025; compliance required by Apr 22, 2026. Adds separate consent for third-party disclosures, data retention limits and a written security program.
A14: LAW-013 | B14: FERPA Regulations (34 CFR Part 99) | C14: Laws & Regulations | D14: laws | E14: Regulation | F14: Privacy | G14: US Department of Education rules on the privacy of student education records, parental and student access rights, and disclosure limits. | H14: https://www.ecfr.gov/current/title-34/subtitle-A/part-99 | I14: U.S. Department of Education | J14: US | L14: Free | M14: Online | Q14: In force | R14: New | S14: Found in search | T14: 46324 | U14: Implements the Family Educational Rights and Privacy Act (1974). Applies to schools receiving federal education funds; relevant to edtech vendors acting as school officials.
A15: LAW-014 | B15: SEC Cybersecurity Risk Management, Strategy, Governance, and Incident Disclosure Rules (Release 33-11216) | C15: Laws & Regulations | D15: laws | E15: Rules | F15: Cybersecurity | G15: SEC rules requiring public companies to disclose material cybersecurity incidents on Form 8-K and describe cyber risk governance annually. | H15: https://www.sec.gov/rules-regulations/2023/07/s7-09-22 | I15: U.S. Securities and Exchange Commission | J15: US | L15: Free | M15: Online | N15: 45174 | Q15: In force | R15: New | S15: Verified | T15: 46324 | U15: Adopted Jul 26, 2023; effective Sep 5, 2023. Form 8-K Item 1.05 due 4 business days after materiality determination; Reg S-K Item 106 annual disclosure. Banking and securities groups petitioned in 2025-26 to rescind or narrow.
A16: LAW-015 | B16: Cyber Incident Reporting for Critical Infrastructure Act of 2022 (CIRCIA) | C16: Laws & Regulations | D16: laws | E16: Law | F16: Cybersecurity | G16: US law directing CISA to require critical infrastructure entities to report covered cyber incidents and ransom payments. | H16: https://www.cisa.gov/topics/cyber-threats-and-advisories/information-sharing/cyber-incident-reporting-critical-infrastructure-act-2022-circia | I16: Cybersecurity and Infrastructure Security Agency (CISA) | J16: US | L16: Free | M16: Online | Q16: Partly in force | R16: New | S16: Verified | T16: 46324 | U16: Enacted Mar 15, 2022; NPRM Apr 4, 2024. Final rule sent to White House (OIRA) review by early Oct 2026; publication expected late 2026. Mandatory 72-hour incident / 24-hour ransom payment reporting starts only once the final rule takes effect.
A17: LAW-016 | B17: FTC Act Section 5 (15 U.S.C. 45) | C17: Laws & Regulations | D17: laws | E17: Law | F17: Privacy; Cybersecurity; AI | G17: US statute prohibiting unfair or deceptive acts or practices; the FTC's main legal basis for privacy, data security and AI enforcement. | H17: https://www.govinfo.gov/link/uscode/15/45 | I17: U.S. Congress | J17: US | L17: Free | M17: Online | Q17: In force | R17: New | S17: Verified | T17: 46324 | U17: Basis for FTC consent orders on data security, privacy misrepresentations and deceptive AI claims. Remedies often include algorithm/data deletion and multi-year security program requirements.
A18: LAW-017 | B18: California Consumer Privacy Act (CCPA), as amended by the CPRA (Cal. Civ. Code 1798.100 et seq.) | C18: Laws & Regulations | D18: laws | E18: Law | F18: Privacy | G18: California statute giving consumers rights to know, delete, correct and opt out of sale or sharing of personal information. | H18: https://leginfo.legislature.ca.gov/faces/codes_displayText.xhtml?division=3.&lawCode=CIV&part=4.&title=1.81.5 | I18: California Legislature | J18: US-CA | L18: Free | M18: Online | N18: 43831 | Q18: In force | R18: New | S18: Found in search | T18: 46324 | U18: Effective Jan 1, 2020; CPRA amendments operative Jan 1, 2023. Enforced by CalPrivacy (California Privacy Protection Agency) and the California Attorney General.
A19: LAW-018 | B19: CCPA Regulations on ADMT, Risk Assessments and Cybersecurity Audits (Cal. Code Regs. tit. 11, § 7000 et seq.) | C19: Laws & Regulations | D19: laws | E19: Rules | F19: Privacy; AI; Cybersecurity | G19: CalPrivacy regulations adding automated decisionmaking technology rights, privacy risk assessments and annual cybersecurity audits to the CCPA rules. | H19: https://cppa.ca.gov/regulations/ccpa_updates.html | I19: California Privacy Protection Agency (CalPrivacy) | J19: US-CA | L19: Free | M19: Online | N19: 46023 | Q19: Partly in force | R19: New | S19: Verified | T19: 46324 | U19: Approved by OAL Sep 22, 2025; effective Jan 1, 2026. ADMT compliance from Jan 1, 2027. Risk assessment attestations due Apr 1, 2028. Cybersecurity audit certifications due Apr 1, 2028/2029/2030 by revenue tier.
A20: LAW-019 | B20: Colorado AI Act (SB 24-205), repealed and reenacted by SB 26-189 (Automated Decision-Making Technology) | C20: Laws & Regulations | D20: laws | E20: Law | F20: AI | G20: Colorado law regulating automated decision-making technology used in consequential decisions such as employment, housing, lending and insurance. | H20: https://leg.colorado.gov/bills/sb26-189 | I20: Colorado General Assembly | J20: US-CO | L20: Free | M20: Online | N20: 46388 | Q20: Enacted - not yet in force | R20: New | S20: Verified | T20: 46324 | U20: SB 24-205 (2024) was delayed to Jun 30, 2026, then rewritten by SB 26-189, signed May 14, 2026: now an ADMT notice, explanation, correction and human-review law effective Jan 1, 2027. AG-only enforcement; 60-day cure.
A21: LAW-020 | B21: Texas Responsible Artificial Intelligence Governance Act (TRAIGA) (HB 149) | C21: Laws & Regulations | D21: laws | E21: Law | F21: AI | G21: Texas law banning certain intentional harmful AI uses, setting disclosure duties for government and health AI uses, and creating an AI sandbox. | H21: https://capitol.texas.gov/tlodocs/89R/billtext/html/HB00149F.htm | I21: Texas Legislature | J21: US-TX | L21: Free | M21: Online | N21: 46023 | Q21: In force | R21: New | S21: Verified | T21: 46324 | U21: Effective Jan 1, 2026 (Bus. & Com. Code ch. 551-554). Attorney General has exclusive enforcement; 60-day cure; penalties up to $200,000 per uncurable violation. Creates 36-month regulatory sandbox and Texas AI Council.
A22: LAW-021 | B22: Texas Data Privacy and Security Act (TDPSA) (HB 4) | C22: Laws & Regulations | D22: laws | E22: Law | F22: Privacy | G22: Texas consumer privacy law granting access, deletion, correction and opt-out rights and requiring data protection assessments. | H22: https://capitol.texas.gov/tlodocs/88R/billtext/html/HB00004F.htm | I22: Texas Legislature | J22: US-TX | L22: Free | M22: Online | N22: 45474 | Q22: In force | R22: New | S22: Verified | T22: 46324 | U22: Effective Jul 1, 2024 (Bus. & Com. Code ch. 541); universal opt-out signal duty from Jan 1, 2025. Applies to most businesses regardless of revenue (small-business carve-out). Attorney General enforces; 30-day cure.
A23: LAW-022 | B23: Virginia Consumer Data Protection Act (VCDPA) (Va. Code 59.1-575 et seq.) | C23: Laws & Regulations | D23: laws | E23: Law | F23: Privacy | G23: Virginia consumer privacy law with access, deletion, correction and opt-out rights, sensitive-data consent and data protection assessments. | H23: https://law.lis.virginia.gov/vacodefull/title59.1/chapter53/ | I23: Virginia General Assembly | J23: US-VA | L23: Free | M23: Online | N23: 44927 | Q23: In force | R23: New | S23: Verified | T23: 46324 | U23: Effective Jan 1, 2023; template for many later state privacy laws. AG enforcement with 30-day cure period. Amended since, incl. added protections for children's data and a 2025 section (59.1-577.1) limiting social media use by minors under 16.
A24: LAW-023 | B24: Illinois Biometric Information Privacy Act (BIPA) (740 ILCS 14) | C24: Laws & Regulations | D24: laws | E24: Law | F24: Privacy | G24: Illinois law requiring notice, written consent and retention policies for biometric identifiers, with a private right of action. | H24: https://www.ilga.gov/legislation/ilcs/ilcs3.asp?ActID=3004&ChapterID=57 | I24: Illinois General Assembly | J24: US-IL | L24: Free | M24: Online | N24: 39724 | Q24: In force | R24: New | S24: Found in search | T24: 46324 | U24: Private right of action: $1,000 negligent / $5,000 intentional or reckless per violation. SB 2979 (Aug 2, 2024) limits recovery to one violation per person per collection method and allows electronic consent.
A25: LAW-024 | B25: NYC Local Law 144 of 2021 (Automated Employment Decision Tools) | C25: Laws & Regulations | D25: laws | E25: Law | F25: AI | G25: New York City law requiring annual bias audits, public audit summaries and candidate notices before employers use automated employment decision tools. | H25: https://www.nyc.gov/site/dca/about/automated-employment-decision-tools.page | I25: New York City Council; Department of Consumer and Worker Protection | J25: US-NY | L25: Free | M25: Online | N25: 45112 | Q25: In force | R25: New | S25: Verified | T25: 46324 | U25: DCWP enforcement began Jul 5, 2023 under implementing rules (6 RCNY 5-300 et seq.). Applies to tools that substantially assist hiring or promotion decisions for NYC jobs.
A26: LAW-025 | B26: NYDFS Cybersecurity Regulation (23 NYCRR Part 500) | C26: Laws & Regulations | D26: laws | E26: Regulation | F26: Cybersecurity | G26: New York DFS rule requiring regulated financial entities to maintain cybersecurity programs, CISO oversight, MFA and 72-hour incident notice. | H26: https://www.dfs.ny.gov/cybersecurity | I26: New York State Department of Financial Services | J26: US-NY | L26: Free | M26: Online | Q26: In force | R26: New | S26: Verified | T26: 46324 | U26: Original rule effective Mar 1, 2017. Second Amendment (Nov 1, 2023) phased in; final requirements (universal MFA, asset inventory) effective Nov 1, 2025. Annual compliance certification due Apr 15.
A27: LAW-026 | B27: Nigeria Data Protection Act 2023 | C27: Laws & Regulations | D27: laws | E27: Law | F27: Privacy | G27: Nigerian statute governing personal data processing, data subject rights, cross-border transfers, and establishing the Nigeria Data Protection Commission. | H27: https://ndpc.gov.ng/wp-content/uploads/2024/03/Nigeria_Data_Protection_Act_2023.pdf | I27: National Assembly of Nigeria | J27: Nigeria | L27: Free | M27: Online | Q27: In force | R27: New | S27: Verified | T27: 46324 | U27: Signed June 12, 2023 (Act No. 37). Replaced the NDPR 2019 regime as primary law; operationalized by the GAID 2025. Data controllers/processors of major importance must register with the NDPC. URL is the official Act text (Gazette reproduction) on ndpc.gov.ng.
A28: LAW-027 | B28: NDPC General Application and Implementation Directive (GAID) 2025 | C28: Laws & Regulations | D28: laws | E28: Rules | F28: Privacy; AI | G28: NDPC directive implementing the Nigeria Data Protection Act 2023, covering compliance audits, DPOs, DPIAs, legitimate interest and emerging tech. | H28: https://ndpc.gov.ng/wp-content/uploads/2025/07/NDP-ACT-GAID-2025-MARCH-20TH.pdf | I28: Nigeria Data Protection Commission (NDPC) | J28: Nigeria | L28: Free | M28: Online | N28: 45919 | Q28: In force | R28: New | S28: Verified | T28: 46324 | U28: Issued Mar 20, 2025; effective Sep 19, 2025. Replaces the NDPR 2019 and its 2020 Implementation Framework. Sets Compliance Audit Return filing and fees, DPO credentials, DPIA template, and rules for AI, blockchain and IoT processing.
A29: LAW-028 | B29: Protection of Personal Information Act 4 of 2013 (POPIA) | C29: Laws & Regulations | D29: laws | E29: Law | F29: Privacy | G29: South African law setting conditions for lawful processing of personal information, data subject rights, breach notification and direct marketing limits. | H29: https://www.gov.za/sites/default/files/gcis_document/201409/3706726-11act4of2013protectionofpersonalinforcorrect.pdf | I29: Parliament of South Africa | J29: South Africa | L29: Free | M29: Online | N29: 44378 | Q29: In force | R29: New | S29: Verified | T29: 46324 | U29: Main provisions commenced Jul 1, 2020 with a one-year grace period; compliance required from Jul 1, 2021. Enforced by the Information Regulator, which also oversees PAIA.
A30: LAW-029 | B30: Kenya Data Protection Act, 2019 (No. 24 of 2019) | C30: Laws & Regulations | D30: laws | E30: Law | F30: Privacy | G30: Kenyan statute regulating personal data processing, data subject rights, controller and processor registration, and the Data Commissioner's powers. | H30: https://new.kenyalaw.org/akn/ke/act/2019/24/eng@2022-12-31 | I30: Parliament of Kenya | J30: Kenya | L30: Free | M30: Online | N30: 43794 | Q30: In force | R30: New | S30: Verified | T30: 46324 | U30: Commenced Nov 25, 2019. Supplemented by the Data Protection (General) Regulations 2021 and registration and complaints regulations. URL is the official Kenya Law consolidated text (version dated 2022-12-31).
A31: LAW-030 | B31: Brazil General Data Protection Law (LGPD) (Law No. 13,709/2018) | C31: Laws & Regulations | D31: laws | E31: Law | F31: Privacy | G31: Brazilian law governing personal data processing, legal bases, data subject rights and international transfers, enforced by the ANPD. | H31: https://www.planalto.gov.br/ccivil_03/_ato2015-2018/2018/lei/l13709compilado.htm | I31: National Congress of Brazil | J31: Brazil | L31: Free | M31: Online | N31: 44092 | Q31: In force | R31: New | S31: Verified | T31: 46324 | U31: In force Sep 18, 2020; administrative sanctions applicable from Aug 1, 2021. ANPD has issued regulations on sanctions, international transfers (SCCs) and DPOs.
A32: LAW-031 | B32: India Digital Personal Data Protection Act, 2023 and DPDP Rules, 2025 | C32: Laws & Regulations | D32: laws | E32: Law | F32: Privacy | G32: Indian law and implementing rules governing digital personal data processing, consent, data principal rights and the Data Protection Board. | H32: https://www.meity.gov.in/static/uploads/2024/06/2bf1f0e9f04e6fb4f8fef35e82c42aa5.pdf | I32: Ministry of Electronics and Information Technology (MeitY) | J32: India | L32: Free | M32: Online | Q32: Partly in force | R32: New | S32: Verified | T32: 46324 | U32: Act assented Aug 11, 2023. Rules notified Nov 13, 2025 (G.S.R. 846(E)) with staged commencement: Board provisions Nov 13, 2025; consent manager provisions Nov 13, 2026; remaining obligations May 13, 2027. URL is the official Act text on meity.gov.in.
A33: LAW-032 | B33: Personal Information Protection and Electronic Documents Act (PIPEDA) (S.C. 2000, c. 5) | C33: Laws & Regulations | D33: laws | E33: Law | F33: Privacy | G33: Canadian federal law governing how private-sector organizations collect, use and disclose personal information in commercial activity. | H33: https://laws-lois.justice.gc.ca/eng/acts/P-8.6/ | I33: Parliament of Canada | J33: Canada | L33: Free | M33: Online | Q33: In force | R33: New | S33: Verified | T33: 46324 | U33: Mandatory breach reporting since Nov 1, 2018. Bill C-27 (CPPA and AIDA) died on prorogation in Jan 2025; watch for reintroduced federal privacy reform. Quebec Law 25 and other provincial laws apply in parallel.
A34: LAW-033 | B34: Singapore Personal Data Protection Act 2012 (PDPA) | C34: Laws & Regulations | D34: laws | E34: Law | F34: Privacy | G34: Singapore law governing private-sector collection, use and disclosure of personal data, including consent, breach notification and Do Not Call rules. | H34: https://sso.agc.gov.sg/Act/PDPA2012 | I34: Parliament of Singapore | J34: Singapore | L34: Free | M34: Online | Q34: In force | R34: New | S34: Found in search | T34: 46324 | U34: Main obligations in force since Jul 2, 2014. 2020 amendments added mandatory breach notification (Feb 1, 2021) and fines up to 10% of Singapore turnover (Oct 1, 2022). Administered by the PDPC.
A35: LAW-034 | B35: Japan Act on the Protection of Personal Information (APPI) | C35: Laws & Regulations | D35: laws | E35: Law | F35: Privacy | G35: Japanese law on business handling of personal information, including purpose limits, third-party provision, cross-border transfers and breach reports. | H35: https://www.ppc.go.jp/en/ | I35: National Diet of Japan; Personal Information Protection Commission | J35: Japan | L35: Free | M35: Online | Q35: In force | R35: New | S35: Verified | T35: 46324 | U35: Enacted 2003; major 2020 amendments in force Apr 1, 2022 (breach reporting, pseudonymized data). PPC adopted a System Reform Policy under the triennial review on Jan 9, 2026; check PPC for amendment bill status. URL is PPC English site with English translations of the Act.
A36: LAW-035 | B36: Council of Europe Framework Convention on Artificial Intelligence and Human Rights, Democracy and the Rule of Law (CETS No. 225) | C36: Laws & Regulations | D36: laws | E36: Treaty | F36: AI | G36: First binding international treaty on AI, requiring parties to ensure AI lifecycle activities respect human rights, democracy and the rule of law. | H36: https://www.coe.int/en-GB/web/conventions/full-list2?module=signatures-by-treaty&treatynum=225 | I36: Council of Europe | J36: Council of Europe | L36: Free | M36: Online | Q36: Enacted - not yet in force | R36: New | S36: Verified | T36: 46324 | U36: Adopted May 17, 2024; opened for signature Sep 5, 2024 (signatories include the EU, UK, US, Canada, Japan). EU ratified May 15, 2026. Enters into force after five ratifications incl. three CoE member states; not yet in force as of Oct 2026.
A37: REG-001 | B37: Federal Trade Commission (FTC) | C37: Regulators & Official Guidance | D37: regulators | E37: Regulator | F37: Privacy; Cybersecurity; AI | G37: US federal agency enforcing consumer protection law on privacy, data security and AI claims, plus COPPA, the GLBA Safeguards Rule and related rules. | H37: https://www.ftc.gov/ | I37: Federal Trade Commission | J37: US | L37: Free | M37: Online | Q37: Active | R37: New | S37: Found in search | T37: 46324 | U37: Publishes enforcement actions, business guidance and policy statements. Key tools: FTC Act Section 5, COPPA Rule, Safeguards Rule, Health Breach Notification Rule.
A38: REG-002 | B38: California Privacy Protection Agency (CalPrivacy) | C38: Regulators & Official Guidance | D38: regulators | E38: Regulator | F38: Privacy; AI | G38: California agency that issues CCPA regulations, enforces the CCPA and runs the data broker registry and Delete Request and Opt-out Platform (DROP). | H38: https://privacy.ca.gov/about-us/about-calprivacy/ | I38: California Privacy Protection Agency | J38: US-CA | L38: Free | M38: Online | Q38: Active | R38: New | S38: Verified | T38: 46324 | U38: Now branded CalPrivacy and uses privacy.ca.gov (cppa.ca.gov still hosts regulations). DROP launched Jan 1, 2026; brokers must process DROP deletions from Aug 1, 2026. ADMT/risk/audit rules effective Jan 1, 2026.
A39: REG-003 | B39: HHS Office for Civil Rights (OCR) - HIPAA | C39: Regulators & Official Guidance | D39: regulators | E39: Regulator | F39: Privacy; Cybersecurity | G39: US HHS office that enforces the HIPAA Privacy, Security and Breach Notification Rules and publishes guidance and enforcement actions. | H39: https://www.hhs.gov/hipaa/index.html | I39: U.S. Department of Health and Human Services | J39: US | L39: Free | M39: Online | Q39: Active | R39: New | S39: Verified | T39: 46324 | U39: Runs the breach portal for incidents affecting 500+ individuals and a risk analysis enforcement initiative. Security Rule update proposed Jan 2025; final action now signalled for 2027.
A40: REG-004 | B40: U.S. Securities and Exchange Commission (SEC) | C40: Regulators & Official Guidance | D40: regulators | E40: Regulator | F40: Cybersecurity | G40: US securities regulator overseeing public company cybersecurity disclosure, Regulation S-P customer data safeguards and cyber-related enforcement. | H40: https://www.sec.gov/ | I40: U.S. Securities and Exchange Commission | J40: US | L40: Free | M40: Online | Q40: Active | R40: New | S40: Verified | T40: 46324 | U40: Cyber and Emerging Technologies Unit (CETU) created Feb 2025. Amended Regulation S-P (incident response and customer notice) adopted 2024 with phased compliance. Rescission petitions on 2023 cyber disclosure rules pending.
A41: REG-005 | B41: Cybersecurity and Infrastructure Security Agency (CISA) - Resources for Lawyers | C41: Regulators & Official Guidance | D41: regulators | E41: Agency | F41: Cybersecurity | G41: US federal cyber defense agency; this CISA page gathers resources for lawyers on incident reporting, information sharing and legal frameworks. | H41: https://www.cisa.gov/about/resources-lawyers | I41: Cybersecurity and Infrastructure Security Agency | J41: US | L41: Free | M41: Online | Q41: Active | R41: New | S41: Verified | T41: 46324 | U41: CISA is writing the CIRCIA incident reporting rule (final rule at OIRA review as of Oct 2026) and publishes Known Exploited Vulnerabilities, Secure by Design and advisories.
A42: REG-006 | B42: NIST Center for Advancing Innovation and Standards for Super Intelligence (CAISSI) | C42: Regulators & Official Guidance | D42: regulators | E42: Agency | F42: AI | G42: NIST center that works with industry on AI model testing, evaluations and voluntary standards; successor to the US AI Safety Institute. | H42: https://www.nist.gov/caisi | I42: National Institute of Standards and Technology | J42: US | L42: Free | M42: Online | Q42: Active | R42: New | S42: Verified | T42: 46324 | U42: Renamed from the US AI Safety Institute to CAISI in June 2025; the nist.gov/caisi page is now titled CAISSI (Center for Advancing Innovation and Standards for Super Intelligence). Publishes frontier model evaluations. NIST also maintains the AI RMF (listed under frameworks).
A43: REG-007 | B43: European Data Protection Board (EDPB) | C43: Regulators & Official Guidance | D43: regulators | E43: Network | F43: Privacy | G43: EU body of national data protection authorities that issues GDPR guidelines and opinions and adopts binding decisions in cross-border cases. | H43: https://www.edpb.europa.eu/ | I43: European Data Protection Board | J43: EU | L43: Free | M43: Online | Q43: Active | R43: New | S43: Verified | T43: 46324 | U43: Key source for GDPR interpretation (guidelines, opinions incl. on AI models, coordinated enforcement reports). EDPB and EDPS issued a joint opinion on the Digital Omnibus in 2026.
... A57: REG-021 | B57: Brazil National Data Protection Agency (ANPD) | C57: Regulators & Official Guidance | D57: regulators | E57: Regulator | F57: Privacy | G57: Brazilian authority that regulates and enforces the LGPD, issuing regulations on sanctions, international transfers and data protection officers. | H57: https://www.gov.br/anpd/pt-br | I57: Autoridade Nacional de Protecao de Dados | J57: Brazil | L57: Free | M57: Online | Q57: Active | R57: New | S57: Found in search | T57: 46324 | U57: Site mainly in Portuguese. Now styled Agência Nacional de Proteção de Dados (agency status). Adopted international transfer regulation with standard contractual clauses (Res. CD/ANPD 19, Aug 23, 2024); recognized the EU as adequate (Res. 32/2026, Jan 2026).
A58: FRM-001 | B58: NIST Cybersecurity Framework (CSF) 2.0 | C58: Frameworks & Standards | D58: frameworks | E58: Framework | F58: Cybersecurity | G58: Voluntary framework of cybersecurity outcomes under six functions (Govern, Identify, Protect, Detect, Respond, Recover) for managing cyber risk. | H58: https://www.nist.gov/cyberframework | I58: NIST | J58: US | K58: All | L58: Free | M58: Online | Q58: Active | R58: New | S58: Verified | T58: 46324 | U58: Version 2.0 released Feb 26, 2024 (NIST CSWP 29); added the Govern function and widened scope beyond critical infrastructure. CSF 1.1 archived. Quick-start guides, profiles and informative references linked from the same page.
A59: FRM-002 | B59: NIST Privacy Framework 1.0 | C59: Frameworks & Standards | D59: frameworks | E59: Framework | F59: Privacy | G59: Voluntary tool for identifying and managing privacy risk, organized into a Core, Profiles and Implementation Tiers, designed to work with the NIST CSF. | H59: https://www.nist.gov/privacy-framework | I59: NIST | J59: US | K59: All | L59: Free | M59: Online | Q59: Active | R59: New | S59: Verified | T59: 46324 | U59: v1.0 (Jan 16, 2020) is the current final version. v1.1 Initial Public Draft (CSWP 40) released Apr 14, 2025, comments closed Jun 13, 2025; aligns Core with CSF 2.0 and adds AI privacy risk content. Final 1.1 not published as of Oct 2026.
A60: FRM-003 | B60: NIST AI Risk Management Framework (AI RMF 1.0) | C60: Frameworks & Standards | D60: frameworks | E60: Framework | F60: AI | G60: Voluntary framework for managing risks of AI systems through four functions (Govern, Map, Measure, Manage) and defined characteristics of trustworthy AI. | H60: https://www.nist.gov/itl/ai-risk-management-framework | I60: NIST | J60: US | K60: All | L60: Free | M60: Online | Q60: Active | R60: New | S60: Verified | T60: 46324 | U60: AI RMF 1.0 (NIST AI 100-1) released Jan 26, 2023. NIST states it is being revised under the White House AI Action Plan. Companion Playbook and profiles (GenAI Profile, AI 600-1); critical infrastructure profile concept note Apr 2026.
A61: FRM-004 | B61: NIST AI 600-1: Generative AI Profile | C61: Frameworks & Standards | D61: frameworks | E61: Framework | F61: AI | G61: Cross-sector AI RMF profile identifying 12 risks unique to or worsened by generative AI, with suggested actions for managing each one. | H61: https://nvlpubs.nist.gov/nistpubs/ai/NIST.AI.600-1.pdf | I61: NIST | J61: US | K61: Intermediate | L61: Free | M61: Download | Q61: Active | R61: New | S61: Verified | T61: 46324 | U61: Published July 26, 2024 as a companion to AI RMF 1.0. Risk categories run from CBRN information or capabilities to value chain and component integration.
A62: FRM-005 | B62: NIST SP 800-53 Rev. 5: Security and Privacy Controls | C62: Frameworks & Standards | D62: frameworks | E62: Control set | F62: Cybersecurity; Privacy | G62: Catalog of security and privacy controls for information systems and organizations; baseline for US federal systems and FedRAMP, widely used elsewhere. | H62: https://csrc.nist.gov/pubs/sp/800/53/r5/upd1/final | I62: NIST | J62: US | K62: Advanced | L62: Free | M62: Download | Q62: Active | R62: New | S62: Verified | T62: 46324 | U62: Rev. 5 final Sept 2020 (updated Dec 10, 2020). Latest catalog release 5.2.0 (Aug 27, 2025), a minor release adding SA-15(13), SA-24 and SI-02(07) and revising SI-07(12). Baselines are in SP 800-53B.
A63: FRM-006 | B63: NIST SP 800-61 Rev. 3: Incident Response Recommendations | C63: Frameworks & Standards | D63: frameworks | E63: Framework | F63: Cybersecurity | G63: NIST guidance for building incident response into cybersecurity risk management, structured as a CSF 2.0 Community Profile. | H63: https://csrc.nist.gov/pubs/sp/800/61/r3/final | I63: NIST | J63: US | K63: Intermediate | L63: Free | M63: Download | Q63: Active | R63: New | S63: Verified | T63: 46324 | U63: Final published Apr 3, 2025. Supersedes SP 800-61 Rev. 2 (2012) and its four-phase incident lifecycle by mapping incident response activities to CSF 2.0 functions.
A64: FRM-007 | B64: ISO/IEC 27001:2022 | C64: Frameworks & Standards | D64: frameworks | E64: Standard | F64: Cybersecurity | G64: Requirements for establishing, maintaining and improving an information security management system (ISMS); the basis for ISO 27001 certification. | H64: https://www.iso.org/standard/27001 | I64: ISO/IEC | J64: Global | K64: Intermediate | L64: Paid (CHF 155) | M64: Download | Q64: Active | R64: New | S64: Found in search | T64: 46324 | U64: Edition 3 published Oct 25, 2022; Annex A has 93 controls aligned to ISO/IEC 27002:2022. Amd 1:2024 adds climate action changes (free). Transition from the 2013 edition ended Oct 31, 2025. Details confirmed on committee.iso.org mirror.
A65: FRM-008 | B65: ISO/IEC 27002:2022 | C65: Frameworks & Standards | D65: frameworks | E65: Control set | F65: Cybersecurity | G65: Reference set of 93 information security controls with implementation guidance, grouped into organizational, people, physical and technological themes. | H65: https://www.iso.org/standard/75652.html | I65: ISO/IEC | J65: Global | K65: Intermediate | L65: Paid (CHF 227) | M65: Download | Q65: Active | R65: New | S65: Verified | T65: 46324 | U65: Edition 3 published Feb 2022; restructured the 2013 edition's 114 controls into 93 controls in four themes with attributes. Guidance companion to ISO/IEC 27001 Annex A.
A66: FRM-009 | B66: ISO/IEC 27701:2025 | C66: Frameworks & Standards | D66: frameworks | E66: Standard | F66: Privacy | G66: Requirements and guidance for a privacy information management system (PIMS) for PII controllers and processors; certifiable on its own. | H66: https://www.iso.org/standard/27701 | I66: ISO/IEC | J66: Global | K66: Intermediate | L66: Paid (CHF 225) | M66: Download | Q66: Active | R66: New | S66: Verified | T66: 46324 | U66: Edition 2 published Oct 2025, replacing ISO/IEC 27701:2019. Now a standalone management system standard rather than an extension of ISO/IEC 27001; adds guidance on personal data in AI systems. Certification transition set by accreditation bodies.
A67: FRM-010 | B67: ISO/IEC 42001:2023 | C67: Frameworks & Standards | D67: frameworks | E67: Standard | F67: AI | G67: Requirements for an AI management system (AIMS) covering responsible development, provision and use of AI systems; certifiable. | H67: https://www.iso.org/standard/42001 | I67: ISO/IEC | J67: Global | K67: Intermediate | L67: Paid (CHF 225) | M67: Download | Q67: Active | R67: New | S67: Found in search | T67: 46324 | U67: Edition 1 published Dec 18, 2023; first certifiable AI management system standard, with AI controls in Annex A. No amendment listed as of Oct 2026. Price and date confirmed on IEC webstore.
A68: FRM-011 | B68: ISO/IEC 23894:2023 | C68: Frameworks & Standards | D68: frameworks | E68: Standard | F68: AI | G68: Guidance on managing risks specific to AI systems, adapting ISO 31000 risk management principles and processes to AI. | H68: https://www.iso.org/standard/77304.html | I68: ISO/IEC | J68: Global | K68: Advanced | L68: Paid (CHF 155) | M68: Download | Q68: Active | R68: New | S68: Verified | T68: 46324 | U68: Edition 1 published Feb 2023. Guidance standard (not certifiable); commonly used alongside ISO/IEC 42001.
A69: FRM-012 | B69: ISO/IEC 29100:2024 | C69: Frameworks & Standards | D69: frameworks | E69: Standard | F69: Privacy | G69: Privacy framework defining common terminology, actors and roles, and 11 privacy principles for protecting PII in ICT systems. | H69: https://www.iso.org/standard/85938.html | I69: ISO/IEC | J69: Global | K69: Beginner | L69: Free (ISO lists CHF 0) | M69: Download | Q69: Active | R69: New | S69: Found in search | T69: 46324 | U69: Edition 2 published Feb 16, 2024; replaces ISO/IEC 29100:2011 and its 2018 amendment. Its principles underpin ISO/IEC 27701 and other ISO privacy standards. Details confirmed on committee.iso.org mirror.
... A148: LRN-031 | B148: Santa Clara Law Certificate Programs (Privacy, High Tech Law) | C148: Learning Center | D148: learning | E148: University program | F148: Tech Law; Privacy | G148: JD certificate programs in privacy law and high tech law at a Silicon Valley law school; suits law students focusing on tech law. | H148: https://law.scu.edu/law/academics/courses-that-satisfy-certificate-requirements/ | I148: Santa Clara University School of Law | J148: US | K148: Advanced | L148: Paid (JD tuition) | M148: In person | Q148: Active | R148: New | S148: Verified | T148: 46324 | U148: Law school homepage (Oct 2026) lists certificates in high tech, international, privacy and public interest law; this page lists qualifying courses. Eligibility and requirements are in the student bulletin.
A149: EVT-001 | B149: SANS AI Cybersecurity Summit Fall 2026 | C149: Events | D149: events | E149: Summit | F149: AI; Cybersecurity | G149: SANS summit on securing AI systems and agents and applying AI in security operations, with talks and workshops in person or online. | H149: https://www.sans.org/cyber-security-training-events/ai-summit-fall-2026 | I149: SANS Institute | J149: US | K149: Intermediate | L149: US$525 in person; US$100 live online | M149: Hybrid | N149: 46328 | O149: 46329 | P149: Arlington, VA, US | Q149: Upcoming | R149: New | S149: Verified | T149: 46324 | U149: Hilton Arlington Rosslyn The Key. Some workshops are in person only.
A150: EVT-002 | B150: Privacy + Security Forum Fall Academy 2026 | C150: Events | D150: events | E150: Conference | F150: Privacy; Cybersecurity; Tech Law | G150: Washington, DC conference on privacy and data security law and practice, organised by Privacy + Security Academy, with CLE/CPE credit. | H150: https://www.privacysecurityacademy.com/psf-fall-conference/ | I150: Privacy + Security Academy | J150: US | K150: All | L150: Paid (price not published) | M150: In person | N150: 46330 | O150: 46332 | P150: Washington, DC, US | Q150: Upcoming | R150: New | S150: Found in search | T150: 46324 | U150: Official site (Oct 2026) lists the Fall Academy as Nov 4-6, 2026 in Washington, DC; end date confirmed. Partner listing (GT Law) puts it at George Washington University. Fees not shown on the homepage; see registration.
A151: EVT-003 | B151: Global Privacy Assembly 2026 (48th Annual Meeting) | C151: Events | D151: events | E151: Conference | F151: Privacy; Tech Law | G151: Annual meeting of the world's data protection and privacy authorities; closed session for members and observers, open programme held within IAPP Congress. | H151: https://globalprivacyassembly.com/?p=6624707 | I151: Global Privacy Assembly | J151: Global | K151: Advanced | L151: Paid (price not published) | M151: In person | N151: 46342 | O151: 46345 | P151: Brussels, Belgium | Q151: Upcoming | R151: New | S151: Verified | T151: 46324 | U151: Closed session 16–17 Nov (Albert Borschette Congress Centre) for GPA members and official observers; open programme 18–19 Nov at SQUARE as part of IAPP Europe Congress. Registration details 'available soon'.
A152: EVT-004 | B152: IAPP Europe Congress 2026 | C152: Events | D152: events | E152: Conference | F152: Privacy; AI; Tech Law | G152: IAPP's main European conference on GDPR, EU data protection, AI governance and enforcement, with training and workshops before the main programme. | H152: https://iapp.org/conference/iapp-europe-congress | I152: IAPP | J152: EU | K152: All | L152: Main conference €1,745 (IAPP members) / €1,945 (non-members); public sector €790, academic €550 | M152: In person | N152: 46342 | O152: 46345 | P152: Brussels, Belgium | Q152: Upcoming | R152: New | S152: Verified | T152: 46324 | U152: Training 16–17 Nov, workshops 17 Nov, main conference 18–19 Nov at SQUARE Brussels Convention Centre. Open programme of the 48th Global Privacy Assembly runs inside the Congress.
A153: EVT-005 | B153: Black Hat Middle East & Africa 2026 | C153: Events | D153: events | E153: Conference | F153: Cybersecurity | G153: Regional Black Hat edition for the Middle East and Africa with security briefings, trainings and a large exhibition. | H153: https://www.blackhat.com/upcoming.html | I153: Black Hat (Informa) | J153: Middle East | K153: All | L153: Paid (price not published) | M153: In person | N153: 46357 | O153: 46359 | P153: Riyadh, Saudi Arabia | Q153: Upcoming | R153: New | S153: Verified | T153: 46324 | U153: At Riyadh Exhibition & Convention Center, Malham.
A154: EVT-006 | B154: IAPP ANZ Summit 2026 | C154: Events | D154: events | E154: Conference | F154: Privacy; AI | G154: IAPP's Australia and New Zealand privacy conference on privacy law reform, AI governance and data protection practice in the region. | H154: https://iapp.org/conference/iapp-anz-summit | I154: IAPP | J154: APAC | K154: All | L154: Main conference AUD 1,745 (members AUD 1,595); training from AUD 1,795 (members) | M154: In person | N154: 46357 | O154: 46360 | P154: Sydney, Australia | Q154: Upcoming | R154: New | S154: Verified | T154: 46324 | U154: Training 1–2 Dec; main conference 3–4 Dec at Hyatt Regency Sydney. CIPP/AU exam offered on the afternoon of 4 Dec.
A155: EVT-007 | B155: ISACA 2026 Virtual Conference | C155: Events | D155: events | E155: Conference | F155: Cybersecurity; Privacy; AI | G155: Online ISACA conference covering IT audit, risk, governance, security and emerging technology topics. | H155: https://www.isaca.org/training-and-events/conferences/isaca-virtual-conference | I155: ISACA | J155: Global | K155: All | L155: Paid (price not published) | M155: Online | N155: 46357 | O155: 46359 | P155: Online | Q155: Upcoming | R155: New | S155: Verified | T155: 46324 | U155: Listed on ISACA's conferences page; pricing not shown in the listing.
A156: EVT-008 | B156: Black Hat Europe 2026 | C156: Events | D156: events | E156: Conference | F156: Cybersecurity | G156: Technical security conference with hands-on trainings and research briefings on vulnerabilities, threats and defence, plus a business hall. | H156: https://www.blackhat.com/upcoming.html | I156: Black Hat (Informa) | J156: UK | K156: Intermediate | L156: Paid (price not published) | M156: In person | N156: 46363 | O156: 46366 | P156: London, UK | Q156: Upcoming | R156: New | S156: Verified | T156: 46324 | U156: At ExCeL London. Trainings run first, followed by two days of briefings and the business hall.
A157: EVT-009 | B157: Gartner Identity & Access Management Summit 2026 | C157: Events | D157: events | E157: Summit | F157: Cybersecurity | G157: Gartner conference for identity and access management leaders on identity governance, access management, PAM and identity threat detection. | H157: https://www.gartner.com/en/conferences/na/identity-access-management-us | I157: Gartner | J157: US | K157: Intermediate | L157: $4,175 standard; $3,550 public sector | M157: In person | N157: 46363 | O157: 46365 | P157: Las Vegas, NV, US | Q157: Upcoming | R157: Notion import | S157: Found in search | T157: 46324 | U157: Confirmed on Gartner's venue and register pages (Oct 2026): Dec 7-9, 2026 at CAESARS FORUM, Las Vegas, NV (not Grapevine, TX). Standard price $4,175; public-sector $3,550 with proof of status.
A158: EVT-010 | B158: SANS Cyber Defense Initiative 2026 | C158: Events | D158: events | E158: Training event | F158: Cybersecurity | G158: SANS year-end training event with multi-day hands-on courses in defence, offence, forensics, cloud, ICS and security leadership. | H158: https://www.sans.org/cyber-security-training-events/cyber-defense-initiative-2026 | I158: SANS Institute | J158: US | K158: Intermediate | L158: Courses US$3,000–US$9,230 (most 6-day courses US$8,780) | M158: Hybrid | N158: 46370 | O158: 46375 | P158: Washington, DC, US | Q158: Upcoming | R158: New | S158: Verified | T158: 46324 | U158: Grand Hyatt Washington or Live Online. Register by 15 Nov for 120 days OnDemand access plus a GIAC attempt. Refund deadline 27 Nov; NetWars included with courses.
A159: EVT-036 | B159: The 17th Annual Sedona Conference Institute 2027: Practical eDiscovery and AI | C159: Events | D159: events | E159: Conference | F159: Tech Law; AI | G159: Two-day Sedona Conference Institute program on practical eDiscovery and AI for litigators, including privilege and GenAI ethics. | H159: https://www.thesedonaconference.org/TSCI_2027 | I159: The Sedona Conference | J159: US | K159: All | L159: Paid (price not published) | M159: In person | N159: 46401 | O159: 46402 | P159: TBA, US | Q159: Upcoming | R159: New | S159: Verified | T159: 46324 | U159: Dates from Sedona's upcoming-events page and agenda (node/11729), fetched Oct 2026. Venue, format and fees not stated on fetched pages; 'In person' assumed, confirm. Link is the official events-page alias.
A160: EVT-011 | B160: Data Privacy and Protection Conference 2027 (DPPC27) | C160: Events | D160: events | E160: Conference | F160: Privacy | G160: Two-day South African conference on data privacy and data protection compliance for organisations. | H160: https://umbonosa.co.za/data-privacy-protection-conference-registration/ | I160: Umbono Conferences and Events | J160: Africa | K160: All | L160: R8,500 in person; R4,500 virtual | M160: In person | N160: 46414 | O160: 46415 | P160: Fourways, Johannesburg, South Africa | Q160: Upcoming | R160: New | S160: Verified | T160: 46324 | U160: Verified on Umbono's site (Oct 2026): 27-28 Jan 2027 at Indaba Hotel, Spa and Conference Centre, Fourways. In person R8,500 or virtual R4,500; early bird R6,375 (in person) until 30 Oct 2026. Event page: umbonosa.co.za/data-privacy-and-protection-conference-2027/
... A186: EVT-030 | B186: Splunk .conf27 | C186: Events | D186: events | E186: Conference | F186: Cybersecurity | G186: Splunk's annual user conference on security operations, observability and data analytics, with technical sessions and training. | H186: https://conf.splunk.com/ | I186: Splunk | J186: US | K186: All | L186: Paid (price not published) | M186: In person | N186: 46664 | O186: 46667 | P186: Chicago, IL, US | Q186: Upcoming | R186: Notion import | S186: Verified | T186: 46324 | U186: At McCormick Place Convention Center. Registration not yet open; site offers sign-up for notifications.
A187: EVT-031 | B187: Global Privacy Assembly 2027 (49th Annual Meeting) | C187: Events | D187: events | E187: Conference | F187: Privacy; Tech Law | G187: Annual meeting of the world's data protection and privacy authorities, hosted in 2027 by Kenya's Office of the Data Protection Commissioner. | H187: https://www.odpc.go.ke/?p=5134 | I187: Global Privacy Assembly / ODPC Kenya | J187: Global | K187: Advanced | L187: Paid (price not published) | M187: In person | P187: Nairobi, Kenya | Q187: Dates TBA | R187: New | S187: Verified | T187: 46324 | U187: Kenya's ODPC won the 2027 hosting bid at GPA 2025 in Seoul. Dates not yet announced; the annual meeting is usually held in October or November.
A188: RES-001 | B188: Google Scholar | C188: Research & Trackers | D188: research | E188: Search engine | F188: General; Tech Law | G188: Free search engine for scholarly literature, including law review articles, US court opinions and technical papers. | H188: https://scholar.google.com/ | I188: Google | J188: Global | K188: All | L188: Free | M188: Online | Q188: Active | R188: Notion import | S188: Found in search | T188: 46324 | U188: Kept from existing library. Use the Case law option for US opinions (state appellate/supreme courts since 1950, federal courts since 1923, SCOTUS since 1791).
A189: RES-002 | B189: data.europa.eu | C189: Research & Trackers | D189: research | E189: Data portal | F189: General | G189: Official EU open data portal with datasets from EU institutions and member states, plus data stories and reports. | H189: https://data.europa.eu/en | I189: Publications Office of the European Union | J189: EU | K189: All | L189: Free | M189: Online | Q189: Active | R189: Notion import | S189: Verified | T189: 46324 | U189: Official EU portal for open data, managed by the Publications Office of the EU.
A190: RES-003 | B190: United Nations Digital Library | C190: Research & Trackers | D190: research | E190: Document library | F190: General; Tech Law | G190: UN repository of resolutions, reports, meeting records and voting data, useful for UN work on cyber, digital and AI issues. | H190: https://digitallibrary.un.org/ | I190: United Nations Dag Hammarskjöld Library | J190: Global | K190: All | L190: Free | M190: Online | Q190: Active | R190: Notion import | S190: Found in search | T190: 46324 | U190: Kept from existing library. Linked from the UN Dag Hammarskjöld Library research guides.
A191: RES-004 | B191: IAPP US State Privacy Legislation Tracker | C191: Research & Trackers | D191: research | E191: Tracker | F191: Privacy; Tech Law | G191: Tracks proposed and enacted comprehensive US state consumer privacy bills, excluding narrow measures such as data security laws. | H191: https://iapp.org/resources/article/us-state-privacy-legislation-tracker | I191: IAPP | J191: US | K191: All | L191: Membership: US$295/yr | M191: Online | Q191: Active | R191: New | S191: Verified | T191: 46324 | U191: Last updated 8 Sep 2026. Labeled member-only (preview visible). IAPP Professional membership US$295/yr per IAPP store.
A192: RES-005 | B192: IAPP Global AI Law and Policy Tracker | C192: Research & Trackers | D192: research | E192: Tracker | F192: AI; Tech Law | G192: Tracks AI legislation, policy and governance developments across jurisdictions worldwide. | H192: https://www.iapp.org/resources/article/global-ai-legislation-tracker | I192: IAPP | J192: Global | K192: All | L192: Membership: US$295/yr | M192: Online | Q192: Active | R192: New | S192: Verified | T192: 46324 | U192: Last updated 6 Oct 2026 (first published Sep 2023). Listed as member content; page links a PDF version.
A193: RES-006 | B193: IAPP US State AI Governance Legislation Tracker | C193: Research & Trackers | D193: research | E193: Tracker | F193: AI; Tech Law | G193: Tracks US state bills that broadly govern AI across sectors and apply to private-sector organizations. | H193: https://iapp.org/resources/article/us-state-ai-governance-legislation-tracker | I193: IAPP | J193: US | K193: All | L193: Membership: US$295/yr | M193: Online | Q193: Active | R193: New | S193: Verified | T193: 46324 | U193: Last updated 28 Apr 2026. Labeled member-only.
A194: RES-007 | B194: IAPP Global Privacy Law and DPA Directory | C194: Research & Trackers | D194: research | E194: Database | F194: Privacy; Tech Law | G194: Directory of data protection authorities and privacy laws by country, with links to each authority and law where available. | H194: https://iapp.org/resources/global-privacy-directory | I194: IAPP | J194: Global | K194: All | L194: Free | M194: Online | Q194: Active | R194: New | S194: Verified | T194: 46324 | U194: No paywall shown at fetch. Described as periodically updated; no last-updated date stated.
A195: RES-008 | B195: ISACA State of Cybersecurity 2026 | C195: Research & Trackers | D195: research | E195: Report | F195: Cybersecurity | G195: Annual ISACA survey of cybersecurity professionals on staffing, budgets, operations, AI and the threat landscape. | H195: https://www.isaca.org/resources/state-of-cybersecurity | I195: ISACA | J195: Global | K195: All | L195: Free | M195: Online | Q195: Active | R195: New | S195: Verified | T195: 46324 | U195: 2026 edition (12th annual); related press releases dated 22 Sep 2026. Free copy offered on the page.
A196: RES-009 | B196: GDPRhub | C196: Research & Trackers | D196: research | E196: Database | F196: Privacy; Tech Law | G196: Free wiki of GDPR decisions by data protection authorities and courts across Europe, summarised in English. | H196: https://gdprhub.eu/index.php?title=Welcome_to_GDPRhub | I196: noyb – European Center for Digital Rights | J196: EU | K196: All | L196: Free | M196: Online | Q196: Active | R196: New | S196: Found in search | T196: 46324 | U196: Root may redirect to the wiki welcome page.
A197: RES-010 | B197: CMS GDPR Enforcement Tracker | C197: Research & Trackers | D197: research | E197: Tracker | F197: Privacy | G197: Database of fines imposed by EU and EEA data protection authorities under the GDPR, filterable by country, sector and article. | H197: https://www.enforcementtracker.com/ | I197: CMS | J197: EU | K197: All | L197: Free | M197: Online | Q197: Active | R197: New | S197: Verified | T197: 46324 | U197: Searchable database of GDPR fines by EU/EEA DPAs, refreshed continuously. CMS also publishes an annual Enforcement Tracker Report (7th edition, Mar 2026).
A198: RES-011 | B198: DLA Piper Data Protection Laws of the World | C198: Research & Trackers | D198: research | E198: Database | F198: Privacy; Tech Law | G198: Comparative guide summarising data protection laws country by country, with side-by-side comparison tools. | H198: https://dlapiperdataprotection.com/ | I198: DLA Piper | J198: Global | K198: All | L198: Free | M198: Online | Q198: Active | R198: New | S198: Verified | T198: 46324 | U198: Covers 160+ jurisdictions; 15th update, now refreshed twice a year. DLA Piper's annual GDPR Fines and Data Breach Survey (January) not listed separately: its URL changes yearly.
A199: RES-012 | B199: OECD.AI Policy Observatory | C199: Research & Trackers | D199: research | E199: Database | F199: AI; Tech Law | G199: OECD platform tracking national AI policies and strategies, with AI data, metrics and the AI Incidents and Hazards Monitor. | H199: https://oecd.ai/en/ | I199: OECD | J199: Global | K199: All | L199: Free | M199: Online | Q199: Active | R199: New | S199: Verified | T199: 46324 | U199: Tracks 900+ national AI policies and initiatives, with live AI data and a policy blog.
... A205: RES-018 | B205: CISA Cybersecurity Advisories | C205: Research & Trackers | D205: research | E205: Database | F205: Cybersecurity | G205: CISA feed of alerts, cybersecurity advisories, ICS advisories and analysis reports on active threats and vulnerabilities. | H205: https://www.cisa.gov/news-events/cybersecurity-advisories | I205: US Cybersecurity and Infrastructure Security Agency (CISA) | J205: US | K205: All | L205: Free | M205: Online | Q205: Active | R205: New | S205: Verified | T205: 46324 | U205: Lists CISA cybersecurity advisories, alerts and ICS/medical advisories. See also CISA's Known Exploited Vulnerabilities catalog.
A206: RES-019 | B206: SSRN | C206: Research & Trackers | D206: research | E206: Document library | F206: Tech Law; General | G206: Open repository of research preprints and working papers, including a large Legal Scholarship Network. | H206: https://www.ssrn.com/index.cfm/en/ | I206: Elsevier | J206: Global | K206: All | L206: Free | M206: Online | Q206: Active | R206: New | S206: Found in search | T206: 46324
A207: RES-020 | B207: arXiv (cs.CR and cs.CY) | C207: Research & Trackers | D207: research | E207: Document library | F207: Cybersecurity; AI | G207: Open-access preprint server; cs.CR covers cryptography and security, cs.CY covers computers and society, including AI policy. | H207: https://arxiv.org/list/cs.CR/recent | I207: arXiv (Cornell University) | J207: Global | K207: All | L207: Free | M207: Online | Q207: Active | R207: New | S207: Verified | T207: 46324 | U207: Computers and Society listing: arxiv.org/list/cs.CY/recent. Preprints are not peer reviewed.
A208: RES-021 | B208: CourtListener | C208: Research & Trackers | D208: research | E208: Database | F208: Tech Law | G208: Free legal research site with US court opinions, oral argument audio and PACER dockets from the RECAP Archive. | H208: https://www.courtlistener.com/ | I208: Free Law Project | J208: US | K208: All | L208: Free | M208: Online | Q208: Active | R208: New | S208: Found in search | T208: 46324 | U208: Run by the nonprofit Free Law Project; free search of US federal and state court opinions, added daily.
A209: RES-022 | B209: EUR-Lex | C209: Research & Trackers | D209: research | E209: Database | F209: Tech Law; Privacy; AI; Cybersecurity | G209: Official database of EU law, including treaties, regulations such as the GDPR and AI Act, directives and EU case law. | H209: https://eur-lex.europa.eu/ | I209: Publications Office of the European Union | J209: EU | K209: All | L209: Free | M209: Online | Q209: Active | R209: New | S209: Verified | T209: 46324 | U209: Official portal for EU law and the Official Journal, run by the EU Publications Office; updated daily.
A210: RES-023 | B210: Privacy Rights Clearinghouse Data Breach Chronology | C210: Research & Trackers | D210: research | E210: Database | F210: Privacy; Cybersecurity | G210: Database of publicly reported US data breaches compiled by Privacy Rights Clearinghouse from government and media sources. | H210: https://privacyrights.org/data-breaches | I210: Privacy Rights Clearinghouse | J210: US | K210: All | L210: Freemium | M210: Online | Q210: Active | R210: New | S210: Verified | T210: 46324 | U210: Online search of breaches; full dataset needs a paid annual subscription (individual or multi-user license, academic discounts; free access possible for some nonprofits/researchers). Free sample files in SQLite/Excel/CSV.
A211: RES-024 | B211: UNCTAD Data Protection and Privacy Legislation Worldwide | C211: Research & Trackers | D211: research | E211: Database | F211: Privacy; Tech Law | G211: UNCTAD map and table showing which countries have data protection and privacy legislation in force or in draft. | H211: https://unctad.org/page/data-protection-and-privacy-legislation-worldwide | I211: UNCTAD | J211: Global | K211: All | L211: Free | M211: Online | Q211: Active | R211: New | S211: Needs check | U211: Part of UNCTAD's Global Cyberlaw Tracker. Not re-verified this session (shared search budget exhausted; site not fetchable).
A212: RES-025 | B212: CVE Program | C212: Research & Trackers | D212: research | E212: Database | F212: Cybersecurity | G212: Catalog of publicly disclosed cybersecurity vulnerabilities with unique CVE identifiers, operated by MITRE with CISA sponsorship. | H212: https://www.cve.org/ | I212: CVE Program (MITRE, CISA-sponsored) | J212: Global | K212: All | L212: Free | M212: Online | Q212: Active | R212: New | S212: Verified | T212: 46324 | U212: Official CVE Program site; successor to cve.mitre.org, whose old content is archived on cve.org.
A213: RES-026 | B213: AlgorithmWatch | C213: Research & Trackers | D213: research | E213: Research center | F213: AI; Tech Law | G213: Berlin-based nonprofit that researches and reports on automated decision-making systems and their effects on society. | H213: https://algorithmwatch.org/en/ | I213: AlgorithmWatch | J213: EU | K213: All | L213: Free | M213: Online | Q213: Active | R213: New | S213: Verified | T213: 46324 | U213: Non-profit research and advocacy organisation on algorithmic decision-making and AI; Swiss office at algorithmwatch.ch.
A214: RES-027 | B214: Georgetown CSET | C214: Research & Trackers | D214: research | E214: Research center | F214: AI; Cybersecurity | G214: Georgetown University think tank producing data-driven research on AI, emerging technology and national security policy. | H214: https://cset.georgetown.edu/ | I214: Center for Security and Emerging Technology, Georgetown University | J214: US | K214: All | L214: Free | M214: Online | Q214: Active | R214: New | S214: Verified | T214: 46324 | U214: Georgetown Walsh School of Foreign Service center for policy research on AI and emerging technology security.
A215: NWS-001 | B215: IAPP Daily Dashboard | C215: Newsletters & News | D215: news | E215: Newsletter | F215: Privacy; AI | G215: Daily email digest of global privacy and data protection news from the IAPP. | H215: https://iapp.org/news/subscriptions | I215: International Association of Privacy Professionals (IAPP) | J215: Global | K215: All | L215: Freemium | M215: Email | Q215: Active | R215: New | S215: Verified | T215: 46324 | U215: Weekday (Mon-Fri) digest of privacy, AI governance and digital responsibility headlines. IAPP also runs a weekly AI Governance Dashboard and regional digests. Free IAPP account needed to subscribe; some content member-only. URL is IAPP's newsletter page.
A216: NWS-002 | B216: Lawfare | C216: Newsletters & News | D216: news | E216: News site | F216: Tech Law; Cybersecurity; General | G216: Analysis of national security law and policy, including cybersecurity, surveillance and AI. | H216: https://www.lawfaremedia.org/ | I216: The Lawfare Institute | J216: United States | K216: Intermediate | L216: Free | M216: Online | Q216: Active | R216: New | S216: Verified | T216: 46324 | U216: Daily articles; free email newsletters available.
A217: NWS-003 | B217: Tech Policy Press | C217: Newsletters & News | D217: news | E217: News site | F217: Tech Law; AI; Privacy | G217: Nonprofit publication covering technology policy, platform governance, AI regulation and democracy. | H217: https://www.techpolicy.press/ | I217: Tech Policy Press | J217: Global | K217: All | L217: Free | M217: Online | Q217: Active | R217: New | S217: Found in search | T217: 46324 | U217: Daily articles, newsletter and podcast (The Sunday Show). Nonprofit publication.
A218: NWS-004 | B218: The Record by Recorded Future News | C218: Newsletters & News | D218: news | E218: News site | F218: Cybersecurity; Privacy | G218: Cybersecurity news covering cybercrime, nation-state hacking, and surveillance and privacy policy. | H218: https://therecord.media/ | I218: Recorded Future News | J218: Global | K218: All | L218: Free | M218: Online | Q218: Active | R218: New | S218: Verified | T218: 46324 | U218: Daily reporting; editorially independent unit of Recorded Future.
A219: NWS-005 | B219: Krebs on Security | C219: Newsletters & News | D219: news | E219: Blog | F219: Cybersecurity | G219: Investigative reporting on cybercrime, data breaches and fraud by journalist Brian Krebs. | H219: https://krebsonsecurity.com/ | I219: Brian Krebs | J219: Global | K219: All | L219: Free | M219: Online | Q219: Active | R219: New | S219: Verified | T219: 46324 | U219: Several in-depth posts per month.
A220: NWS-006 | B220: Dark Reading | C220: Newsletters & News | D220: news | E220: News site | F220: Cybersecurity | G220: Cybersecurity news and analysis for security professionals. | H220: https://www.darkreading.com/ | I220: Informa TechTarget | J220: Global | K220: Intermediate | L220: Free | M220: Online | Q220: Active | R220: New | S220: Found in search | T220: 46324 | U220: Daily; free email newsletters. Part of Informa TechTarget.
A221: NWS-007 | B221: BleepingComputer | C221: Newsletters & News | D221: news | E221: News site | F221: Cybersecurity | G221: Daily news on ransomware, vulnerabilities, data breaches and malware, plus technical guides. | H221: https://www.bleepingcomputer.com/ | I221: BleepingComputer | J221: Global | K221: All | L221: Free | M221: Online | Q221: Active | R221: New | S221: Found in search | T221: 46324 | U221: Daily.
...

Sheet Sections
A1: Section Key | B1: Code | C1: Display Name | D1: Description | E1: Resources | F1: Links to check | G1: Kept from Notion
A2: laws | B2: LAW | C2: Laws & Regulations | D2: Primary legal texts on privacy, cybersecurity and AI, with current status and key dates. | E2: =COUNTIF(Resources!$D:$D,A2) -> 35 | F2: =COUNTIFS(Resources!$D:$D,A2,Resources!$S:$S,"Needs check") -> 0 | G2: =COUNTIFS(Resources!$D:$D,A2,Resources!$R:$R,"Notion import") -> 0
A3: regulators | B3: REG | C3: Regulators & Official Guidance | D3: Authorities that enforce these laws and the guidance they publish. | E3: =COUNTIF(Resources!$D:$D,A3) -> 21 | F3: =COUNTIFS(Resources!$D:$D,A3,Resources!$S:$S,"Needs check") -> 0 | G3: =COUNTIFS(Resources!$D:$D,A3,Resources!$R:$R,"Notion import") -> 0
A4: frameworks | B4: FRM | C4: Frameworks & Standards | D4: Standards, control sets and principles used to build, assess and audit programs. | E4: =COUNTIF(Resources!$D:$D,A4) -> 30 | F4: =COUNTIFS(Resources!$D:$D,A4,Resources!$S:$S,"Needs check") -> 0 | G4: =COUNTIFS(Resources!$D:$D,A4,Resources!$R:$R,"Notion import") -> 0
A5: certifications | B5: CRT | C5: Certifications | D5: Professional credentials in privacy, security, AI governance and e-discovery, beginner to expert. | E5: =COUNTIF(Resources!$D:$D,A5) -> 30 | F5: =COUNTIFS(Resources!$D:$D,A5,Resources!$S:$S,"Needs check") -> 0 | G5: =COUNTIFS(Resources!$D:$D,A5,Resources!$R:$R,"Notion import") -> 0
A6: learning | B6: LRN | C6: Learning Center | D6: Courses, labs and training programs. Courses teach a subject; they are not certifications. | E6: =COUNTIF(Resources!$D:$D,A6) -> 31 | F6: =COUNTIFS(Resources!$D:$D,A6,Resources!$S:$S,"Needs check") -> 0 | G6: =COUNTIFS(Resources!$D:$D,A6,Resources!$R:$R,"Notion import") -> 14
A7: events | B7: EVT | C7: Events | D7: Conferences, summits and training events from November 2026 onward. | E7: =COUNTIF(Resources!$D:$D,A7) -> 39 | F7: =COUNTIFS(Resources!$D:$D,A7,Resources!$S:$S,"Needs check") -> 0 | G7: =COUNTIFS(Resources!$D:$D,A7,Resources!$R:$R,"Notion import") -> 4
A8: research | B8: RES | C8: Research & Trackers | D8: Law trackers, enforcement databases, annual reports and research libraries. | E8: =COUNTIF(Resources!$D:$D,A8) -> 27 | F8: =COUNTIFS(Resources!$D:$D,A8,Resources!$S:$S,"Needs check") -> 1 | G8: =COUNTIFS(Resources!$D:$D,A8,Resources!$R:$R,"Notion import") -> 3
A9: news | B9: NWS | C9: Newsletters & News | D9: News sites, newsletters and law-firm blogs that track developments. | E9: =COUNTIF(Resources!$D:$D,A9) -> 22 | F9: =COUNTIFS(Resources!$D:$D,A9,Resources!$S:$S,"Needs check") -> 1 | G9: =COUNTIFS(Resources!$D:$D,A9,Resources!$R:$R,"Notion import") -> 0
A10: podcasts | B10: POD | C10: Podcasts | D10: Shows on privacy, security, AI policy and tech law. | E10: =COUNTIF(Resources!$D:$D,A10) -> 20 | F10: =COUNTIFS(Resources!$D:$D,A10,Resources!$S:$S,"Needs check") -> 0 | G10: =COUNTIFS(Resources!$D:$D,A10,Resources!$R:$R,"Notion import") -> 8
A11: books | B11: BKS | C11: Books & Literature | D11: Foundational and current books and articles, checked against real publications. | E11: =COUNTIF(Resources!$D:$D,A11) -> 31 | F11: =COUNTIFS(Resources!$D:$D,A11,Resources!$S:$S,"Needs check") -> 0 | G11: =COUNTIFS(Resources!$D:$D,A11,Resources!$R:$R,"Notion import") -> 0
A12: tools | B12: TLS | C12: Tools & Templates | D12: Free or low-cost tools, templates and assessment kits practitioners use. | E12: =COUNTIF(Resources!$D:$D,A12) -> 25 | F12: =COUNTIFS(Resources!$D:$D,A12,Resources!$S:$S,"Needs check") -> 0 | G12: =COUNTIFS(Resources!$D:$D,A12,Resources!$R:$R,"Notion import") -> 0
A13: communities | B13: COM | C13: Communities & Associations | D13: Professional bodies, advocacy groups and communities to join. | E13: =COUNTIF(Resources!$D:$D,A13) -> 21 | F13: =COUNTIFS(Resources!$D:$D,A13,Resources!$S:$S,"Needs check") -> 0 | G13: =COUNTIFS(Resources!$D:$D,A13,Resources!$R:$R,"Notion import") -> 0
A14: jobs | B14: JOB | C14: Job Boards & Careers | D14: Where to find roles, plus salary and workforce data. | E14: =COUNTIF(Resources!$D:$D,A14) -> 21 | F14: =COUNTIFS(Resources!$D:$D,A14,Resources!$S:$S,"Needs check") -> 0 | G14: =COUNTIFS(Resources!$D:$D,A14,Resources!$R:$R,"Notion import") -> 13
C15: Total | E15: =SUM(E2:E14) -> 353 | F15: =SUM(F2:F14) -> 2 | G15: =SUM(G2:G14) -> 42

Sheet Coverage
A1: Resources by section and topic
A2: A resource can carry several topics, so rows add up to more than the section total.
A4: Section | B4: Cybersecurity | C4: Privacy | D4: AI | E4: Tech Law | F4: General | G4: Section total
A5: Laws & Regulations | B5: =COUNTIFS(Resources!$D:$D,"laws",Resources!$F:$F,"*Cybersecurity*") -> 10 | C5: =COUNTIFS(Resources!$D:$D,"laws",Resources!$F:$F,"*Privacy*") -> 24 | D5: =COUNTIFS(Resources!$D:$D,"laws",Resources!$F:$F,"*AI*") -> 8 | E5: =COUNTIFS(Resources!$D:$D,"laws",Resources!$F:$F,"*Tech Law*") -> 2 | F5: =COUNTIFS(Resources!$D:$D,"laws",Resources!$F:$F,"*General*") -> 0 | G5: =COUNTIF(Resources!$D:$D,"laws") -> 35
A6: Regulators & Official Guidance | B6: =COUNTIFS(Resources!$D:$D,"regulators",Resources!$F:$F,"*Cybersecurity*") -> 6 | C6: =COUNTIFS(Resources!$D:$D,"regulators",Resources!$F:$F,"*Privacy*") -> 15 | D6: =COUNTIFS(Resources!$D:$D,"regulators",Resources!$F:$F,"*AI*") -> 10 | E6: =COUNTIFS(Resources!$D:$D,"regulators",Resources!$F:$F,"*Tech Law*") -> 0 | F6: =COUNTIFS(Resources!$D:$D,"regulators",Resources!$F:$F,"*General*") -> 0 | G6: =COUNTIF(Resources!$D:$D,"regulators") -> 21
A7: Frameworks & Standards | B7: =COUNTIFS(Resources!$D:$D,"frameworks",Resources!$F:$F,"*Cybersecurity*") -> 17 | C7: =COUNTIFS(Resources!$D:$D,"frameworks",Resources!$F:$F,"*Privacy*") -> 9 | D7: =COUNTIFS(Resources!$D:$D,"frameworks",Resources!$F:$F,"*AI*") -> 11 | E7: =COUNTIFS(Resources!$D:$D,"frameworks",Resources!$F:$F,"*Tech Law*") -> 2 | F7: =COUNTIFS(Resources!$D:$D,"frameworks",Resources!$F:$F,"*General*") -> 2 | G7: =COUNTIF(Resources!$D:$D,"frameworks") -> 30
A8: Certifications | B8: =COUNTIFS(Resources!$D:$D,"certifications",Resources!$F:$F,"*Cybersecurity*") -> 20 | C8: =COUNTIFS(Resources!$D:$D,"certifications",Resources!$F:$F,"*Privacy*") -> 11 | D8: =COUNTIFS(Resources!$D:$D,"certifications",Resources!$F:$F,"*AI*") -> 5 | E8: =COUNTIFS(Resources!$D:$D,"certifications",Resources!$F:$F,"*Tech Law*") -> 8 | F8: =COUNTIFS(Resources!$D:$D,"certifications",Resources!$F:$F,"*General*") -> 0 | G8: =COUNTIF(Resources!$D:$D,"certifications") -> 30
A9: Learning Center | B9: =COUNTIFS(Resources!$D:$D,"learning",Resources!$F:$F,"*Cybersecurity*") -> 23 | C9: =COUNTIFS(Resources!$D:$D,"learning",Resources!$F:$F,"*Privacy*") -> 6 | D9: =COUNTIFS(Resources!$D:$D,"learning",Resources!$F:$F,"*AI*") -> 14 | E9: =COUNTIFS(Resources!$D:$D,"learning",Resources!$F:$F,"*Tech Law*") -> 2 | F9: =COUNTIFS(Resources!$D:$D,"learning",Resources!$F:$F,"*General*") -> 7 | G9: =COUNTIF(Resources!$D:$D,"learning") -> 31
A10: Events | B10: =COUNTIFS(Resources!$D:$D,"events",Resources!$F:$F,"*Cybersecurity*") -> 21 | C10: =COUNTIFS(Resources!$D:$D,"events",Resources!$F:$F,"*Privacy*") -> 18 | D10: =COUNTIFS(Resources!$D:$D,"events",Resources!$F:$F,"*AI*") -> 20 | E10: =COUNTIFS(Resources!$D:$D,"events",Resources!$F:$F,"*Tech Law*") -> 18 | F10: =COUNTIFS(Resources!$D:$D,"events",Resources!$F:$F,"*General*") -> 0 | G10: =COUNTIF(Resources!$D:$D,"events") -> 39
A11: Research & Trackers | B11: =COUNTIFS(Resources!$D:$D,"research",Resources!$F:$F,"*Cybersecurity*") -> 10 | C11: =COUNTIFS(Resources!$D:$D,"research",Resources!$F:$F,"*Privacy*") -> 9 | D11: =COUNTIFS(Resources!$D:$D,"research",Resources!$F:$F,"*AI*") -> 9 | E11: =COUNTIFS(Resources!$D:$D,"research",Resources!$F:$F,"*Tech Law*") -> 14 | F11: =COUNTIFS(Resources!$D:$D,"research",Resources!$F:$F,"*General*") -> 4 | G11: =COUNTIF(Resources!$D:$D,"research") -> 27
A12: Newsletters & News | B12: =COUNTIFS(Resources!$D:$D,"news",Resources!$F:$F,"*Cybersecurity*") -> 12 | C12: =COUNTIFS(Resources!$D:$D,"news",Resources!$F:$F,"*Privacy*") -> 10 | D12: =COUNTIFS(Resources!$D:$D,"news",Resources!$F:$F,"*AI*") -> 10 | E12: =COUNTIFS(Resources!$D:$D,"news",Resources!$F:$F,"*Tech Law*") -> 11 | F12: =COUNTIFS(Resources!$D:$D,"news",Resources!$F:$F,"*General*") -> 4 | G12: =COUNTIF(Resources!$D:$D,"news") -> 22
A13: Podcasts | B13: =COUNTIFS(Resources!$D:$D,"podcasts",Resources!$F:$F,"*Cybersecurity*") -> 10 | C13: =COUNTIFS(Resources!$D:$D,"podcasts",Resources!$F:$F,"*Privacy*") -> 10 | D13: =COUNTIFS(Resources!$D:$D,"podcasts",Resources!$F:$F,"*AI*") -> 11 | E13: =COUNTIFS(Resources!$D:$D,"podcasts",Resources!$F:$F,"*Tech Law*") -> 7 | F13: =COUNTIFS(Resources!$D:$D,"podcasts",Resources!$F:$F,"*General*") -> 4 | G13: =COUNTIF(Resources!$D:$D,"podcasts") -> 20
A14: Books & Literature | B14: =COUNTIFS(Resources!$D:$D,"books",Resources!$F:$F,"*Cybersecurity*") -> 10 | C14: =COUNTIFS(Resources!$D:$D,"books",Resources!$F:$F,"*Privacy*") -> 22 | D14: =COUNTIFS(Resources!$D:$D,"books",Resources!$F:$F,"*AI*") -> 8 | E14: =COUNTIFS(Resources!$D:$D,"books",Resources!$F:$F,"*Tech Law*") -> 17 | F14: =COUNTIFS(Resources!$D:$D,"books",Resources!$F:$F,"*General*") -> 0 | G14: =COUNTIF(Resources!$D:$D,"books") -> 31
A15: Tools & Templates | B15: =COUNTIFS(Resources!$D:$D,"tools",Resources!$F:$F,"*Cybersecurity*") -> 14 | C15: =COUNTIFS(Resources!$D:$D,"tools",Resources!$F:$F,"*Privacy*") -> 7 | D15: =COUNTIFS(Resources!$D:$D,"tools",Resources!$F:$F,"*AI*") -> 8 | E15: =COUNTIFS(Resources!$D:$D,"tools",Resources!$F:$F,"*Tech Law*") -> 1 | F15: =COUNTIFS(Resources!$D:$D,"tools",Resources!$F:$F,"*General*") -> 0 | G15: =COUNTIF(Resources!$D:$D,"tools") -> 25
A16: Communities & Associations | B16: =COUNTIFS(Resources!$D:$D,"communities",Resources!$F:$F,"*Cybersecurity*") -> 10 | C16: =COUNTIFS(Resources!$D:$D,"communities",Resources!$F:$F,"*Privacy*") -> 11 | D16: =COUNTIFS(Resources!$D:$D,"communities",Resources!$F:$F,"*AI*") -> 10 | E16: =COUNTIFS(Resources!$D:$D,"communities",Resources!$F:$F,"*Tech Law*") -> 8 | F16: =COUNTIFS(Resources!$D:$D,"communities",Resources!$F:$F,"*General*") -> 0 | G16: =COUNTIF(Resources!$D:$D,"communities") -> 21
A17: Job Boards & Careers | B17: =COUNTIFS(Resources!$D:$D,"jobs",Resources!$F:$F,"*Cybersecurity*") -> 18 | C17: =COUNTIFS(Resources!$D:$D,"jobs",Resources!$F:$F,"*Privacy*") -> 5 | D17: =COUNTIFS(Resources!$D:$D,"jobs",Resources!$F:$F,"*AI*") -> 2 | E17: =COUNTIFS(Resources!$D:$D,"jobs",Resources!$F:$F,"*Tech Law*") -> 1 | F17: =COUNTIFS(Resources!$D:$D,"jobs",Resources!$F:$F,"*General*") -> 2 | G17: =COUNTIF(Resources!$D:$D,"jobs") -> 21
A18: All sections | B18: =SUM(B5:B17) -> 181 | C18: =SUM(C5:C17) -> 157 | D18: =SUM(D5:D17) -> 126 | E18: =SUM(E5:E17) -> 91 | F18: =SUM(F5:F17) -> 23 | G18: =SUM(G5:G17) -> 353

Sheet Removed
A1: Name | B1: Old Section | C1: Reason | D1: Replaced By
A2: Notion | B2: Tools | C2: General productivity software, not specific to cyber, privacy, AI or tech law. | D2: Tools & Templates section
A3: Google Drive | B3: Tools | C3: General productivity software, not specific to cyber, privacy, AI or tech law. | D3: Tools & Templates section
A4: Google Sheets | B4: Tools | C4: General productivity software, not specific to cyber, privacy, AI or tech law. | D4: Tools & Templates section
A5: Google Calendar | B5: Tools | C5: General productivity software, not specific to cyber, privacy, AI or tech law. | D5: Tools & Templates section
A6: Google Keep | B6: Tools | C6: General productivity software, not specific to cyber, privacy, AI or tech law. | D6: Tools & Templates section
A7: Trello | B7: Tools | C7: General productivity software, not specific to cyber, privacy, AI or tech law. | D7: Tools & Templates section
A8: Slack | B8: Tools | C8: General productivity software, not specific to cyber, privacy, AI or tech law. | D8: Tools & Templates section
A9: Lucidchart | B9: Tools | C9: General productivity software, not specific to cyber, privacy, AI or tech law. | D9: Tools & Templates section
A10: Figma | B10: Tools | C10: General productivity software, not specific to cyber, privacy, AI or tech law. | D10: Tools & Templates section
A11: Slidesgo | B11: Tools | C11: General productivity software, not specific to cyber, privacy, AI or tech law. | D11: Tools & Templates section
A12: Genially | B12: Tools | C12: General productivity software, not specific to cyber, privacy, AI or tech law. | D12: Tools & Templates section
... A17: Forest | B17: Tools | C17: General productivity software, not specific to cyber, privacy, AI or tech law. | D17: Tools & Templates section
A18: TED-Ed | B18: Learning Center | C18: General education, no specific relevance.
A19: TED | B19: Learning Center | C19: General talks, no specific relevance.
A20: OER Commons | B20: Learning Center | C20: General open courseware.
A21: OpenStax | B21: Learning Center | C21: General open textbooks.
A22: Skillshare | B22: Learning Center | C22: Creative and business courses, little in these fields.
A23: Google Arts & Culture | B23: Learning Center | C23: Off-topic.
A24: Reflection Toolkit | B24: Learning Center | C24: No link and unclear relevance.
A25: Yale Online | B25: Learning Center | C25: No cyber, privacy, AI or tech-law courses found.
A26: PubMed | B26: Research | C26: Biomedical literature, off-topic. | D26: Google Scholar, SSRN, arXiv
A27: Google Public Data Explorer | B27: Research | C27: General statistics, off-topic.
A28: Eurostat | B28: Research | C28: General EU statistics, off-topic. | D28: data.europa.eu, EUR-Lex
A29: National Renewable Energy Laboratory Research | B29: Research | C29: Energy research, off-topic.
A30: Goodreads | B30: Books & Literature | C30: General book tracker.
A31: Privacy Books (list page) | B31: Books & Literature | C31: Repeated about 25 titles three times, used a third party's Amazon affiliate links, and included titles and authors that could not be matched to real books. | D31: 31 individual book and article entries
A32: Cybersecurity Books (list page) | B32: Books & Literature | C32: List page with no verified entries. | D32: Individual book entries
A33: NinjaJobs | B33: Job Boards | C33: Site now redirects to a recruiting firm with no job listings.
A34: ISEC Jobs | B34: Job Boards | C34: Site shut down on June 30, 2026.
A35: The Tech Law Hangout | B35: Podcasts | C35: No episodes since September 2024; mostly IP and corporate law. | D35: Scaling Laws, Lawfare Daily
A36: BSidesNYC Conference (Oct 2024) | B36: Events | C36: Past event. The 2026 edition is also over and 2027 dates are not announced. | D36: Re-add when dates are published
A37: Hack The Railroad 2024 | B37: Events | C37: Past event; next edition not found.
A38: Innovative Cybersecurity Summit – Scottsdale 2024 | B38: Events | C38: Past event; next edition not found.
A39: The Data Security and Privacy Summit | B39: Events | C39: No date listed; next edition not found.
A40: Data Privacy Conference (Sep 2024) | B40: Events | C40: Past event; next edition not found.
A41: Compliance Week (Feb 2025) | B41: Events | C41: Past event. The organizer lists only the May 2026 edition so far. | D41: Re-add when 2027 dates are published
A42: CAMLIS Conference (Oct 2024) | B42: Events | C42: Past event. The 2026 edition is over and 2027 dates are not announced. | D42: Re-add when dates are published
A43: Cyber Security Training at SANS Network Security (Sep 2024) | B43: Events | C43: Past event. | D43: SANS Network Security 2027
A44: DEF CON 32 (Aug 2024) | B44: Events | C44: Past event. | D44: DEF CON 35
A45: Splunk .conf24 (Jun 2024) | B45: Events | C45: Past event. | D45: Splunk .conf27
A46: NICE Conference & Expo | B46: Events | C46: Old entry had no date. | D46: 18th Annual NICE Conference & Expo (2027)
A47: GLEG – GIAC Law of Data Security & Investigations | B47: Certifications (new) | C47: GIAC has put GLEG in abeyance; it is no longer available for purchase.
A48: Gartner Identity & Access Management Summit USA (Dec 2024) | B48: Events | C48: Past event. | D48: Gartner Identity & Access Management Summit 2026
A49: Cybersecurity Conferences 2024–2025 (list page) | B49: Events | C49: Outdated list page. | D49: Individual event entries
A50: Certifications (placeholder page) | B50: Certifications | C50: Empty page in Notion. | D50: Certifications section (31 entries)
A51: Cyber SN (duplicate row) | B51: Job Boards | C51: Duplicate of another row. | D51: CyberSN
A52: (untitled row) | B52: Certifications | C52: Blank row in Notion.
